fckafde_shortener/__init__.py
fckafde_shortener-0.1.0.dist-info/LICENSE
fckafde_shortener-0.1.0.dist-info/METADATA
fckafde_shortener-0.1.0.dist-info/WHEEL
fckafde_shortener-0.1.0.dist-info/top_level.txt
fckafde_shortener-0.1.0.dist-info/RECORD
